pyxelmagic/__init__.py
pyxelmagic/pyxelmagic.py
pyxelmagic-1.1.1.dist-info/METADATA
pyxelmagic-1.1.1.dist-info/WHEEL
pyxelmagic-1.1.1.dist-info/top_level.txt
pyxelmagic-1.1.1.dist-info/RECORD
